plak/.DS_Store
plak/__init__.py
plak/__main__.py
plak/domain.py
plak/main.py
plak/server.py
plak/sshkey.py
plak-0.1.0.dist-info/LICENSE
plak-0.1.0.dist-info/METADATA
plak-0.1.0.dist-info/WHEEL
plak-0.1.0.dist-info/entry_points.txt
plak-0.1.0.dist-info/RECORD
