Metadata-Version: 2.1
Name: plak
Version: 0.1.0
Summary: 
Author: Oscar Hugo Paz
Author-email: oscar@plak.io
Requires-Python: >=3.12,<4.0
Classifier: Programming Language :: Python :: 3
Classifier: Programming Language :: Python :: 3.12
Requires-Dist: pytest (>=8.3.2,<9.0.0)
Requires-Dist: typer[all] (>=0.12.3,<0.13.0)
